{
	"configurations" : 
	[
		{
			"directories" : 
			[
				{
					"build" : ".",
					"minimumCMakeVersion" : 
					{
						"string" : "2.6"
					},
					"projectIndex" : 0,
					"source" : ".",
					"targetIndexes" : 
					[
						0,
						1
					]
				}
			],
			"name" : "Debug",
			"projects" : 
			[
				{
					"directoryIndexes" : 
					[
						0
					],
					"name" : "stockviewer",
					"targetIndexes" : 
					[
						0,
						1
					]
				}
			],
			"targets" : 
			[
				{
					"directoryIndex" : 0,
					"id" : "glad::@6890427a1f51a3e7e1df",
					"jsonFile" : "target-glad-Debug-aa8cb4ca7c144c048913.json",
					"name" : "glad",
					"projectIndex" : 0
				},
				{
					"directoryIndex" : 0,
					"id" : "stockviewer::@6890427a1f51a3e7e1df",
					"jsonFile" : "target-stockviewer-Debug-1a4b75b2faee574914fc.json",
					"name" : "stockviewer",
					"projectIndex" : 0
				}
			]
		}
	],
	"kind" : "codemodel",
	"paths" : 
	{
		"build" : "/home/parallels/Desktop/dev/CppND-Capstone-TimeSeries/build",
		"source" : "/home/parallels/Desktop/dev/CppND-Capstone-TimeSeries"
	},
	"version" : 
	{
		"major" : 2,
		"minor" : 0
	}
}
